{
    "os": "Linux-5.4.0-195-generic-x86_64-with-glibc2.31",
    "python": "3.10.14",
    "heartbeatAt": "2024-09-16T13:20:03.409422",
    "startedAt": "2024-09-16T13:20:02.315363",
    "docker": null,
    "cuda": null,
    "args": [
        "--local_rank=0",
        "--model_name_or_path",
        "/data/SyL/model/vicuna-7b-v1.5",
        "--version",
        "plain",
        "--data_path",
        "/data/SyL/LLaVA/data_process/merged_instruction.json",
        "--image_folder",
        "/data/SyL/LLaVA/custom_data/images",
        "--event_folder",
        "/data/SyL/LLaVA/custom_data/events",
        "--vision_tower",
        "/data/SyL/model/clip-vit-large-patch14-336",
        "--mm_projector_type",
        "mlp2x_gelu",
        "--tune_mm_mlp_adapter",
        "True",
        "--mm_vision_select_layer",
        "-2",
        "--mm_use_im_start_end",
        "False",
        "--mm_use_im_patch_token",
        "False",
        "--bf16",
        "True",
        "--output_dir",
        "/data/SyL/LLaVA/checkpoints/llava-v1.5-7b-pretrain",
        "--num_train_epochs",
        "4",
        "--per_device_train_batch_size",
        "8",
        "--per_device_eval_batch_size",
        "4",
        "--gradient_accumulation_steps",
        "4",
        "--evaluation_strategy",
        "no",
        "--save_strategy",
        "steps",
        "--save_steps",
        "100",
        "--save_total_limit",
        "1",
        "--learning_rate",
        "1e-3",
        "--weight_decay",
        "0.",
        "--warmup_ratio",
        "0.03",
        "--lr_scheduler_type",
        "cosine",
        "--logging_steps",
        "1",
        "--tf32",
        "True",
        "--model_max_length",
        "2048",
        "--gradient_checkpointing",
        "True",
        "--dataloader_num_workers",
        "4",
        "--lazy_preprocess",
        "True",
        "--report_to",
        "wandb"
    ],
    "state": "running",
    "program": "/data/SyL/Event_RGB/deepspeed_train.py",
    "codePathLocal": "deepspeed_train.py",
    "codePath": "deepspeed_train.py",
    "host": "user-X12DPG-OA6",
    "username": "root",
    "executable": "/home/user/anaconda3/envs/llava/bin/python",
    "cpu_count": 32,
    "cpu_count_logical": 64,
    "cpu_freq": {
        "current": 1649.4227187500003,
        "min": 800.0,
        "max": 3500.0
    },
    "cpu_freq_per_core": [
        {
            "current": 3304.077,
            "min": 800.0,
            "max": 3500.0
        },
        {
            "current": 854.595,
            "min": 800.0,
            "max": 3500.0
        },
        {
            "current": 1300.439,
            "min": 800.0,
            "max": 3500.0
        },
        {
            "current": 3309.85,
            "min": 800.0,
            "max": 3500.0
        },
        {
            "current": 799.893,
            "min": 800.0,
            "max": 3500.0
        },
        {
            "current": 799.184,
            "min": 800.0,
            "max": 3500.0
        },
        {
            "current": 800.555,
            "min": 800.0,
            "max": 3500.0
        },
        {
            "current": 800.625,
            "min": 800.0,
            "max": 3500.0
        },
        {
            "current": 2780.07,
            "min": 800.0,
            "max": 3500.0
        },
        {
            "current": 2658.613,
            "min": 800.0,
            "max": 3500.0
        },
        {
            "current": 896.775,
            "min": 800.0,
            "max": 3500.0
        },
        {
            "current": 800.876,
            "min": 800.0,
            "max": 3500.0
        },
        {
            "current": 800.54,
            "min": 800.0,
            "max": 3500.0
        },
        {
            "current": 800.0,
            "min": 800.0,
            "max": 3500.0
        },
        {
            "current": 800.781,
            "min": 800.0,
            "max": 3500.0
        },
        {
            "current": 3303.317,
            "min": 800.0,
            "max": 3500.0
        },
        {
            "current": 1505.68,
            "min": 800.0,
            "max": 3500.0
        },
        {
            "current": 2463.302,
            "min": 800.0,
            "max": 3500.0
        },
        {
            "current": 1447.003,
            "min": 800.0,
            "max": 3500.0
        },
        {
            "current": 1182.175,
            "min": 800.0,
            "max": 3500.0
        },
        {
            "current": 3300.0,
            "min": 800.0,
            "max": 3500.0
        },
        {
            "current": 2238.855,
            "min": 800.0,
            "max": 3500.0
        },
        {
            "current": 2283.26,
            "min": 800.0,
            "max": 3500.0
        },
        {
            "current": 2274.704,
            "min": 800.0,
            "max": 3500.0
        },
        {
            "current": 1205.826,
            "min": 800.0,
            "max": 3500.0
        },
        {
            "current": 800.0,
            "min": 800.0,
            "max": 3500.0
        },
        {
            "current": 3300.053,
            "min": 800.0,
            "max": 3500.0
        },
        {
            "current": 799.939,
            "min": 800.0,
            "max": 3500.0
        },
        {
            "current": 1361.769,
            "min": 800.0,
            "max": 3500.0
        },
        {
            "current": 3300.0,
            "min": 800.0,
            "max": 3500.0
        },
        {
            "current": 938.54,
            "min": 800.0,
            "max": 3500.0
        },
        {
            "current": 2524.242,
            "min": 800.0,
            "max": 3500.0
        },
        {
            "current": 3303.32,
            "min": 800.0,
            "max": 3500.0
        },
        {
            "current": 900.0,
            "min": 800.0,
            "max": 3500.0
        },
        {
            "current": 3067.582,
            "min": 800.0,
            "max": 3500.0
        },
        {
            "current": 3300.0,
            "min": 800.0,
            "max": 3500.0
        },
        {
            "current": 799.091,
            "min": 800.0,
            "max": 3500.0
        },
        {
            "current": 799.945,
            "min": 800.0,
            "max": 3500.0
        },
        {
            "current": 800.0,
            "min": 800.0,
            "max": 3500.0
        },
        {
            "current": 800.445,
            "min": 800.0,
            "max": 3500.0
        },
        {
            "current": 3300.0,
            "min": 800.0,
            "max": 3500.0
        },
        {
            "current": 2900.0,
            "min": 800.0,
            "max": 3500.0
        },
        {
            "current": 872.996,
            "min": 800.0,
            "max": 3500.0
        },
        {
            "current": 800.658,
            "min": 800.0,
            "max": 3500.0
        },
        {
            "current": 800.797,
            "min": 800.0,
            "max": 3500.0
        },
        {
            "current": 800.0,
            "min": 800.0,
            "max": 3500.0
        },
        {
            "current": 801.167,
            "min": 800.0,
            "max": 3500.0
        },
        {
            "current": 3300.0,
            "min": 800.0,
            "max": 3500.0
        },
        {
            "current": 1544.014,
            "min": 800.0,
            "max": 3500.0
        },
        {
            "current": 3245.331,
            "min": 800.0,
            "max": 3500.0
        },
        {
            "current": 1116.399,
            "min": 800.0,
            "max": 3500.0
        },
        {
            "current": 1321.757,
            "min": 800.0,
            "max": 3500.0
        },
        {
            "current": 3300.0,
            "min": 800.0,
            "max": 3500.0
        },
        {
            "current": 1239.537,
            "min": 800.0,
            "max": 3500.0
        },
        {
            "current": 1219.988,
            "min": 800.0,
            "max": 3500.0
        },
        {
            "current": 2881.843,
            "min": 800.0,
            "max": 3500.0
        },
        {
            "current": 1206.783,
            "min": 800.0,
            "max": 3500.0
        },
        {
            "current": 800.0,
            "min": 800.0,
            "max": 3500.0
        },
        {
            "current": 3300.0,
            "min": 800.0,
            "max": 3500.0
        },
        {
            "current": 840.646,
            "min": 800.0,
            "max": 3500.0
        },
        {
            "current": 2114.886,
            "min": 800.0,
            "max": 3500.0
        },
        {
            "current": 3299.194,
            "min": 800.0,
            "max": 3500.0
        },
        {
            "current": 931.92,
            "min": 800.0,
            "max": 3500.0
        },
        {
            "current": 2638.783,
            "min": 800.0,
            "max": 3500.0
        }
    ],
    "disk": {
        "/": {
            "total": 438.05088806152344,
            "used": 58.82142639160156
        }
    },
    "gpu": "NVIDIA GeForce RTX 3090",
    "gpu_count": 8,
    "gpu_devices": [
        {
            "name": "NVIDIA GeForce RTX 3090",
            "memory_total": 25769803776
        },
        {
            "name": "NVIDIA GeForce RTX 3090",
            "memory_total": 25769803776
        },
        {
            "name": "NVIDIA GeForce RTX 3090",
            "memory_total": 25769803776
        },
        {
            "name": "NVIDIA GeForce RTX 3090",
            "memory_total": 25769803776
        },
        {
            "name": "NVIDIA GeForce RTX 3090",
            "memory_total": 25769803776
        },
        {
            "name": "NVIDIA GeForce RTX 3090",
            "memory_total": 25769803776
        },
        {
            "name": "NVIDIA GeForce RTX 3090",
            "memory_total": 25769803776
        },
        {
            "name": "NVIDIA GeForce RTX 3090",
            "memory_total": 25769803776
        }
    ],
    "memory": {
        "total": 503.54224014282227
    }
}
